{"pageProps":{"plant":{"title":"Baby Tears","scientific_name":"Soleirolia soleirolii","toxicity_level":"Safe","summary":"Baby Tears is completely safe for cats and forms a dense carpet of tiny leaves.","image":"https://images.unsplash.com/photo-1592194996308-7b43878e84a6?ixlib=rb-4.0.3&w=800&h=600&fit=crop&auto=format","care_difficulty":"Medium","common_names":["Baby Tears","Mind-Your-Own-Business"],"is_flower":false,"image2":"","image3":"","pet_moment":"","symptoms":[],"clinical_signs":[],"safe_alternatives":[],"sources":[],"contentHtml":"","what_to_do_html":"","slug":"baby-tears"}},"__N_SSG":true}